{
  "basics": {
    "name": "CHEN Yanxin",
    "label": "Ph.D. Student in Artificial Intelligence",
    "email": "yanxinchen26@m.fudan.edu.cn",
    "phone": "",
    "website": "https://ssssuperc.github.io",
    "summary": "Ph.D. student in Artificial Intelligence at Fudan University, focusing on long video understanding, video large models, retrieval-augmented generation, and large-scale VLM training infrastructure.",
    "location": {
      "address": "",
      "postalCode": "",
      "city": "Shanghai",
      "countryCode": "China",
      "region": ""
    },
    "profiles": [
      {
        "network": "GitHub",
        "username": "SSSSuperC",
        "url": "https://github.com/SSSSuperC"
      }
    ]
  },
  "work": [
    {
      "company": "MOSS-VL",
      "position": "Core Contributor",
      "startDate": "2026",
      "endDate": "",
      "summary": "Large-scale VLM pretraining and SFT workflow.",
      "highlights": [
        "Responsible for four-stage pretraining and the full SFT workflow, including ablation experiments and formal training runs.",
        "Experienced with thousand-GPU cluster training and debugging training-framework, data, NCCL communication, and deadlock issues."
      ]
    }
  ],
  "education": [
    {
      "institution": "Fudan University",
      "area": "Ph.D. in Artificial Intelligence",
      "studyType": "Ph.D.",
      "startDate": "2026.09",
      "endDate": "Present",
      "gpa": null,
      "courses": []
    }
  ],
  "skills": [
    {
      "name": "AI Algorithms",
      "keywords": [
        "Large Language Models",
        "Video Large Models",
        "Long Video Understanding",
        "RAG",
        "SFT/RL Post-training",
        "Linear Attention"
      ]
    },
    {
      "name": "Training Infrastructure",
      "keywords": [
        "Megatron-LM",
        "TransformerEngine",
        "DeepSpeed",
        "FlashAttention",
        "FlashAttention-3",
        "TP/PP/DP Parallelism",
        "Activation Recomputation"
      ]
    },
    {
      "name": "Engineering",
      "keywords": [
        "Python",
        "C++",
        "PyTorch",
        "Linux/Bash",
        "NCCL Debugging",
        "Cluster Debugging"
      ]
    }
  ],
  "languages": [],
  "interests": [
    {
      "name": "Research",
      "keywords": [
        "Efficient VLM Training",
        "Long-context Video Modeling",
        "VLM Post-training",
        "Low-precision Training"
      ]
    }
  ],
  "references": [],
  "publications": [
    {
      "name": "ProEchoMem: Enhancing Long Video Understanding via Multi-Trace Probe-Echo Memory",
      "publisher": "SIGIR 2026",
      "releaseDate": "2026",
      "website": "",
      "summary": "Co-first author. Proposed the PN-RAG framework for probe generation, structured annotation, and fine-grained reranking in long-video understanding."
    }
  ],
  "presentations": [],
  "teaching": [],
  "portfolio": []
}
